{
    "2025-05-02 00:00:00": [
        {
            "user": "U07ERHUJ3A9",
            "type": "message",
            "ts": "1746197506.825409",
            "edited": {
                "user": "U07ERHUJ3A9",
                "ts": "1746197560.000000"
            },
            "client_msg_id": "515dee36-a961-446e-bd34-7aa303e10c5c",
            "text": "April 29 - May 1\n\u2022 Went thru the care repos and care.ohc.network\n\u2022 End sem exams are going\n\u2022 Learning Typescript\n\u2022 Exploring how Eslint works and figuring out how to fix the warnings\nNext\n\u2022 open an issue with details to fix",
            "team": "TC99SV7B6",
            "blocks": [
                {
                    "type": "rich_text",
                    "block_id": "yjkxM",
                    "elements": [
                        {
                            "type": "rich_text_section",
                            "elements": [
                                {
                                    "type": "text",
                                    "text": "April 29 - May 1\n"
                                }
                            ]
                        },
                        {
                            "type": "rich_text_list",
                            "elements": [
                                {
                                    "type": "rich_text_section",
                                    "elements": [
                                        {
                                            "type": "text",
                                            "text": "Went thru the care repos and care.ohc.network"
                                        }
                                    ]
                                },
                                {
                                    "type": "rich_text_section",
                                    "elements": [
                                        {
                                            "type": "text",
                                            "text": "End sem exams are going"
                                        }
                                    ]
                                },
                                {
                                    "type": "rich_text_section",
                                    "elements": [
                                        {
                                            "type": "text",
                                            "text": "Learning Typescript"
                                        }
                                    ]
                                },
                                {
                                    "type": "rich_text_section",
                                    "elements": [
                                        {
                                            "type": "text",
                                            "text": "Exploring how Eslint works and figuring out how to fix the warnings"
                                        }
                                    ]
                                }
                            ],
                            "style": "bullet",
                            "indent": 0,
                            "offset": 0,
                            "border": 0
                        },
                        {
                            "type": "rich_text_section",
                            "elements": [
                                {
                                    "type": "text",
                                    "text": "Next\n"
                                }
                            ]
                        },
                        {
                            "type": "rich_text_list",
                            "elements": [
                                {
                                    "type": "rich_text_section",
                                    "elements": [
                                        {
                                            "type": "text",
                                            "text": "open an issue with details to fix"
                                        }
                                    ]
                                }
                            ],
                            "style": "bullet",
                            "indent": 0,
                            "offset": 0,
                            "border": 0
                        }
                    ]
                }
            ],
            "reactions": [
                {
                    "name": "rocket",
                    "users": [
                        "U02TDGQQPMJ",
                        "U07NGSB2MUP"
                    ],
                    "count": 2
                }
            ]
        }
    ],
    "2025-05-12 00:00:00": [
        {
            "user": "U07ERHUJ3A9",
            "type": "message",
            "ts": "1747041157.995569",
            "edited": {
                "user": "U07ERHUJ3A9",
                "ts": "1747041318.000000"
            },
            "client_msg_id": "ade403d0-3901-4d74-9ad6-f2839add132d",
            "text": "May 5-9\n\u2022 Exams and Looking up issues\nMay 10-12\n\u2022 Got assigned to an <https://github.com/ohcnetwork/care_fe/issues/11946|issue>, Never used react before so ive been trying to understand how it works, and what im dealing with.",
            "team": "TC99SV7B6",
            "blocks": [
                {
                    "type": "rich_text",
                    "block_id": "kdyjm",
                    "elements": [
                        {
                            "type": "rich_text_section",
                            "elements": [
                                {
                                    "type": "text",
                                    "text": "May 5-9\n"
                                }
                            ]
                        },
                        {
                            "type": "rich_text_list",
                            "elements": [
                                {
                                    "type": "rich_text_section",
                                    "elements": [
                                        {
                                            "type": "text",
                                            "text": "Exams and Looking up issues"
                                        }
                                    ]
                                }
                            ],
                            "style": "bullet",
                            "indent": 0,
                            "border": 0
                        },
                        {
                            "type": "rich_text_section",
                            "elements": [
                                {
                                    "type": "text",
                                    "text": "May 10-12\n"
                                }
                            ]
                        },
                        {
                            "type": "rich_text_list",
                            "elements": [
                                {
                                    "type": "rich_text_section",
                                    "elements": [
                                        {
                                            "type": "text",
                                            "text": "Got assigned to an "
                                        },
                                        {
                                            "type": "link",
                                            "url": "https://github.com/ohcnetwork/care_fe/issues/11946",
                                            "text": "issue"
                                        },
                                        {
                                            "type": "text",
                                            "text": ", Never used react before so ive been trying to understand how it works, and what im dealing with."
                                        }
                                    ]
                                }
                            ],
                            "style": "bullet",
                            "indent": 0,
                            "border": 0
                        }
                    ]
                }
            ],
            "reactions": [
                {
                    "name": "rocket",
                    "users": [
                        "U08G3EL0XFS",
                        "U082GUAL80N"
                    ],
                    "count": 2
                }
            ]
        }
    ],
    "2025-05-16 00:00:00": [
        {
            "user": "U07ERHUJ3A9",
            "type": "message",
            "ts": "1747389446.846949",
            "edited": {
                "user": "U07ERHUJ3A9",
                "ts": "1747389477.000000"
            },
            "client_msg_id": "b59cfba9-3309-449e-bc73-f437b92cef44",
            "text": "May 10-15\n\u2022 Learned React\n\u2022 Huddles with yaswanth, regarding the <https://github.com/ohcnetwork/care_fe/pull/12308|issue>, Only to find out its way more complicated than we initially thought.\n\u2022 Still trying to fix it but kind of keeping it on the side while working on other issues\nNext\n\u2022 Fix eslint warnings\n\u2022 Look for new issues",
            "team": "TC99SV7B6",
            "blocks": [
                {
                    "type": "rich_text",
                    "block_id": "HuN1f",
                    "elements": [
                        {
                            "type": "rich_text_section",
                            "elements": [
                                {
                                    "type": "text",
                                    "text": "May 10-15\n"
                                }
                            ]
                        },
                        {
                            "type": "rich_text_list",
                            "elements": [
                                {
                                    "type": "rich_text_section",
                                    "elements": [
                                        {
                                            "type": "text",
                                            "text": "Learned React"
                                        }
                                    ]
                                },
                                {
                                    "type": "rich_text_section",
                                    "elements": [
                                        {
                                            "type": "text",
                                            "text": "Huddles with yaswanth, regarding the "
                                        },
                                        {
                                            "type": "link",
                                            "url": "https://github.com/ohcnetwork/care_fe/pull/12308",
                                            "text": "issue"
                                        },
                                        {
                                            "type": "text",
                                            "text": ", Only to find out its way more complicated than we initially thought."
                                        }
                                    ]
                                },
                                {
                                    "type": "rich_text_section",
                                    "elements": [
                                        {
                                            "type": "text",
                                            "text": "Still trying to fix it but kind of keeping it on the side while working on other issues"
                                        }
                                    ]
                                }
                            ],
                            "style": "bullet",
                            "indent": 0,
                            "border": 0
                        },
                        {
                            "type": "rich_text_section",
                            "elements": [
                                {
                                    "type": "text",
                                    "text": "Next\n"
                                }
                            ]
                        },
                        {
                            "type": "rich_text_list",
                            "elements": [
                                {
                                    "type": "rich_text_section",
                                    "elements": [
                                        {
                                            "type": "text",
                                            "text": "Fix eslint warnings"
                                        }
                                    ]
                                },
                                {
                                    "type": "rich_text_section",
                                    "elements": [
                                        {
                                            "type": "text",
                                            "text": "Look for new issues"
                                        }
                                    ]
                                }
                            ],
                            "style": "bullet",
                            "indent": 0,
                            "border": 0
                        }
                    ]
                }
            ]
        }
    ],
    "2025-05-28 00:00:00": [
        {
            "user": "U07ERHUJ3A9",
            "type": "message",
            "ts": "1748451676.279769",
            "client_msg_id": "6e24b782-b541-4d52-9b44-70d0ec46ab9b",
            "text": "May 28\n\u2022 Working on <https://github.com/ohcnetwork/care_fe/issues/12411|#12411>\n\u2022 Went through different approaches for solving it\n\u2022 Learning more about tailwindcss\nNext:\n\u2022 Raise PR",
            "team": "TC99SV7B6",
            "blocks": [
                {
                    "type": "rich_text",
                    "block_id": "HtKcv",
                    "elements": [
                        {
                            "type": "rich_text_section",
                            "elements": [
                                {
                                    "type": "text",
                                    "text": "May 28\n"
                                }
                            ]
                        },
                        {
                            "type": "rich_text_list",
                            "elements": [
                                {
                                    "type": "rich_text_section",
                                    "elements": [
                                        {
                                            "type": "text",
                                            "text": "Working on "
                                        },
                                        {
                                            "type": "link",
                                            "url": "https://github.com/ohcnetwork/care_fe/issues/12411",
                                            "text": "#12411",
                                            "unsafe": true
                                        }
                                    ]
                                },
                                {
                                    "type": "rich_text_section",
                                    "elements": [
                                        {
                                            "type": "text",
                                            "text": "Went through different approaches for solving it"
                                        }
                                    ]
                                },
                                {
                                    "type": "rich_text_section",
                                    "elements": [
                                        {
                                            "type": "text",
                                            "text": "Learning more about tailwindcss"
                                        }
                                    ]
                                }
                            ],
                            "style": "bullet",
                            "indent": 0,
                            "border": 0
                        },
                        {
                            "type": "rich_text_section",
                            "elements": [
                                {
                                    "type": "text",
                                    "text": "Next:\n"
                                }
                            ]
                        },
                        {
                            "type": "rich_text_list",
                            "elements": [
                                {
                                    "type": "rich_text_section",
                                    "elements": [
                                        {
                                            "type": "text",
                                            "text": "Raise PR"
                                        }
                                    ]
                                }
                            ],
                            "style": "bullet",
                            "indent": 0,
                            "border": 0
                        }
                    ]
                }
            ]
        }
    ],
    "2025-05-29 00:00:00": [
        {
            "user": "U07ERHUJ3A9",
            "type": "message",
            "ts": "1748538440.826569",
            "client_msg_id": "7dea3f0e-0b3c-4249-ba4f-217af7ab9f8e",
            "text": "28 May\n\u2022 Went through different approaches to solve the <https://github.com/ohcnetwork/care_fe/issues/12411|problem> \n\u2022 Learned a lot about tailwind\n\u2022 Raised the <https://github.com/ohcnetwork/care_fe/pull/12456|PR> \nNext:\n\u2022 Look for new issues",
            "team": "TC99SV7B6",
            "blocks": [
                {
                    "type": "rich_text",
                    "block_id": "Xq45h",
                    "elements": [
                        {
                            "type": "rich_text_section",
                            "elements": [
                                {
                                    "type": "text",
                                    "text": "28 May\n"
                                }
                            ]
                        },
                        {
                            "type": "rich_text_list",
                            "elements": [
                                {
                                    "type": "rich_text_section",
                                    "elements": [
                                        {
                                            "type": "text",
                                            "text": "Went through different approaches to solve the "
                                        },
                                        {
                                            "type": "link",
                                            "url": "https://github.com/ohcnetwork/care_fe/issues/12411",
                                            "text": "problem"
                                        },
                                        {
                                            "type": "text",
                                            "text": " "
                                        }
                                    ]
                                },
                                {
                                    "type": "rich_text_section",
                                    "elements": [
                                        {
                                            "type": "text",
                                            "text": "Learned a lot about tailwind"
                                        }
                                    ]
                                },
                                {
                                    "type": "rich_text_section",
                                    "elements": [
                                        {
                                            "type": "text",
                                            "text": "Raised the "
                                        },
                                        {
                                            "type": "link",
                                            "url": "https://github.com/ohcnetwork/care_fe/pull/12456",
                                            "text": "PR"
                                        },
                                        {
                                            "type": "text",
                                            "text": " "
                                        }
                                    ]
                                }
                            ],
                            "style": "bullet",
                            "indent": 0,
                            "offset": 0,
                            "border": 0
                        },
                        {
                            "type": "rich_text_section",
                            "elements": [
                                {
                                    "type": "text",
                                    "text": "Next:\n"
                                }
                            ]
                        },
                        {
                            "type": "rich_text_list",
                            "elements": [
                                {
                                    "type": "rich_text_section",
                                    "elements": [
                                        {
                                            "type": "text",
                                            "text": "Look for new issues"
                                        }
                                    ]
                                }
                            ],
                            "style": "bullet",
                            "indent": 0,
                            "offset": 0,
                            "border": 0
                        }
                    ]
                }
            ]
        }
    ],
    "2025-06-02 00:00:00": [
        {
            "user": "U07ERHUJ3A9",
            "type": "message",
            "ts": "1748890263.956309",
            "client_msg_id": "a8c47c0a-7f8c-4d4c-aa9c-bf4fe2ba0706",
            "text": "31st May - 2nd June:\n\u2022 Worked on #<https://github.com/ohcnetwork/care_fe/issues/11946|11946>, Spend a awful lot of time debugging. Still haven't figured out whats going wrong. Im starting to believe its possessed by something.\n\u2022 Busy with some volunteering works.\n\u2022 Opened #<https://github.com/ohcnetwork/care_fe/issues/12491|12491>(Got closed but i found a bug trying to fix that)\n\u2022 Exploring other approaches to fix #<https://github.com/ohcnetwork/care_fe/pull/12456|12456>\nNext:\n\u2022 Open the issue\n\u2022 Find more bugs :bug:",
            "team": "TC99SV7B6",
            "blocks": [
                {
                    "type": "rich_text",
                    "block_id": "UTjH3",
                    "elements": [
                        {
                            "type": "rich_text_section",
                            "elements": [
                                {
                                    "type": "text",
                                    "text": "31st May - 2nd June:\n"
                                }
                            ]
                        },
                        {
                            "type": "rich_text_list",
                            "elements": [
                                {
                                    "type": "rich_text_section",
                                    "elements": [
                                        {
                                            "type": "text",
                                            "text": "Worked on #"
                                        },
                                        {
                                            "type": "link",
                                            "url": "https://github.com/ohcnetwork/care_fe/issues/11946",
                                            "text": "11946"
                                        },
                                        {
                                            "type": "text",
                                            "text": ", Spend a awful lot of time debugging. Still haven't figured out whats going wrong. Im starting to believe its possessed by something."
                                        }
                                    ]
                                },
                                {
                                    "type": "rich_text_section",
                                    "elements": [
                                        {
                                            "type": "text",
                                            "text": "Busy with some volunteering works."
                                        }
                                    ]
                                },
                                {
                                    "type": "rich_text_section",
                                    "elements": [
                                        {
                                            "type": "text",
                                            "text": "Opened #"
                                        },
                                        {
                                            "type": "link",
                                            "url": "https://github.com/ohcnetwork/care_fe/issues/12491",
                                            "text": "12491"
                                        },
                                        {
                                            "type": "text",
                                            "text": "(Got closed but i found a bug trying to fix that)"
                                        }
                                    ]
                                },
                                {
                                    "type": "rich_text_section",
                                    "elements": [
                                        {
                                            "type": "text",
                                            "text": "Exploring other approaches to fix #"
                                        },
                                        {
                                            "type": "link",
                                            "url": "https://github.com/ohcnetwork/care_fe/pull/12456",
                                            "text": "12456"
                                        }
                                    ]
                                }
                            ],
                            "style": "bullet",
                            "indent": 0,
                            "offset": 0,
                            "border": 0
                        },
                        {
                            "type": "rich_text_section",
                            "elements": [
                                {
                                    "type": "text",
                                    "text": "Next:\n"
                                }
                            ]
                        },
                        {
                            "type": "rich_text_list",
                            "elements": [
                                {
                                    "type": "rich_text_section",
                                    "elements": [
                                        {
                                            "type": "text",
                                            "text": "Open the issue"
                                        }
                                    ]
                                },
                                {
                                    "type": "rich_text_section",
                                    "elements": [
                                        {
                                            "type": "text",
                                            "text": "Find more bugs "
                                        },
                                        {
                                            "type": "emoji",
                                            "name": "bug",
                                            "unicode": "1f41b"
                                        }
                                    ]
                                }
                            ],
                            "style": "bullet",
                            "indent": 0,
                            "offset": 0,
                            "border": 0
                        }
                    ]
                }
            ]
        }
    ],
    "2025-06-04 00:00:00": [
        {
            "user": "U07ERHUJ3A9",
            "type": "message",
            "ts": "1749056890.334999",
            "client_msg_id": "bdd1242c-4d87-4fe1-8cce-ac4ff2d49bbe",
            "text": "3rd and 4th June\n\u2022 Raised care_fe#<https://github.com/ohcnetwork/care_fe/pull/12501|12501> \n\u2022 Opened care_fe#<https://github.com/ohcnetwork/care_fe/issues/12506|12506> \n\u2022 Raised care_fe#<https://github.com/ohcnetwork/care_fe/pull/12516|12516>\n\u2022 Opened care_fe#<https://github.com/ohcnetwork/care_fe/issues/12513|12513> and started working on it and later found out that it was already raised 13 days ago\nNext\n\u2022 Look for more issues",
            "team": "TC99SV7B6",
            "blocks": [
                {
                    "type": "rich_text",
                    "block_id": "RwDtt",
                    "elements": [
                        {
                            "type": "rich_text_section",
                            "elements": [
                                {
                                    "type": "text",
                                    "text": "3rd and 4th June\n"
                                }
                            ]
                        },
                        {
                            "type": "rich_text_list",
                            "elements": [
                                {
                                    "type": "rich_text_section",
                                    "elements": [
                                        {
                                            "type": "text",
                                            "text": "Raised care_fe#"
                                        },
                                        {
                                            "type": "link",
                                            "url": "https://github.com/ohcnetwork/care_fe/pull/12501",
                                            "text": "12501"
                                        },
                                        {
                                            "type": "text",
                                            "text": " "
                                        }
                                    ]
                                },
                                {
                                    "type": "rich_text_section",
                                    "elements": [
                                        {
                                            "type": "text",
                                            "text": "Opened care_fe#"
                                        },
                                        {
                                            "type": "link",
                                            "url": "https://github.com/ohcnetwork/care_fe/issues/12506",
                                            "text": "12506"
                                        },
                                        {
                                            "type": "text",
                                            "text": " "
                                        }
                                    ]
                                },
                                {
                                    "type": "rich_text_section",
                                    "elements": [
                                        {
                                            "type": "text",
                                            "text": "Raised care_fe#"
                                        },
                                        {
                                            "type": "link",
                                            "url": "https://github.com/ohcnetwork/care_fe/pull/12516",
                                            "text": "12516"
                                        }
                                    ]
                                },
                                {
                                    "type": "rich_text_section",
                                    "elements": [
                                        {
                                            "type": "text",
                                            "text": "Opened care_fe#"
                                        },
                                        {
                                            "type": "link",
                                            "url": "https://github.com/ohcnetwork/care_fe/issues/12513",
                                            "text": "12513"
                                        },
                                        {
                                            "type": "text",
                                            "text": " and started working on it and later found out that it was already raised 13 days ago"
                                        }
                                    ]
                                }
                            ],
                            "style": "bullet",
                            "indent": 0,
                            "offset": 0,
                            "border": 0
                        },
                        {
                            "type": "rich_text_section",
                            "elements": [
                                {
                                    "type": "text",
                                    "text": "Next\n"
                                }
                            ]
                        },
                        {
                            "type": "rich_text_list",
                            "elements": [
                                {
                                    "type": "rich_text_section",
                                    "elements": [
                                        {
                                            "type": "text",
                                            "text": "Look for more issues"
                                        }
                                    ]
                                }
                            ],
                            "style": "bullet",
                            "indent": 0,
                            "offset": 0,
                            "border": 0
                        }
                    ]
                }
            ],
            "reactions": [
                {
                    "name": "rocket",
                    "users": [
                        "U07UB6TQWRE"
                    ],
                    "count": 1
                }
            ]
        }
    ],
    "2025-06-06 00:00:00": [
        {
            "user": "U07ERHUJ3A9",
            "type": "message",
            "ts": "1749227712.665399",
            "edited": {
                "user": "U07ERHUJ3A9",
                "ts": "1749228187.000000"
            },
            "client_msg_id": "b77b83fb-28ca-4003-a5da-27d2a64dd9f1",
            "text": "5th and 6th June\n\u2022 Opened <https://github.com/ohcnetwork/care_fe/issues/12523|Misalignment and inconsistency in the UI of 'Add Files' dropdown in encounter files>\n\u2022 Raised <https://github.com/ohcnetwork/care_fe/pull/12524|fix: Misalignment and inconsistency in the UI of 'Add Files' dropdown in encounter files>\n\u2022 Opened and started working on <https://github.com/ohcnetwork/care_fe/issues/12526|Enhance the UI of the patient encounters file menu for mobile screens>, Later it became clear that an issue addressing the same prob already exists\nNext\n\u2022 Take it easy\n\u2022 Find more bugs",
            "team": "TC99SV7B6",
            "blocks": [
                {
                    "type": "rich_text",
                    "block_id": "1b34M",
                    "elements": [
                        {
                            "type": "rich_text_section",
                            "elements": [
                                {
                                    "type": "text",
                                    "text": "5th and 6th June\n"
                                }
                            ]
                        },
                        {
                            "type": "rich_text_list",
                            "elements": [
                                {
                                    "type": "rich_text_section",
                                    "elements": [
                                        {
                                            "type": "text",
                                            "text": "Opened "
                                        },
                                        {
                                            "type": "link",
                                            "url": "https://github.com/ohcnetwork/care_fe/issues/12523",
                                            "text": "Misalignment and inconsistency in the UI of 'Add Files' dropdown in encounter files"
                                        }
                                    ]
                                },
                                {
                                    "type": "rich_text_section",
                                    "elements": [
                                        {
                                            "type": "text",
                                            "text": "Raised "
                                        },
                                        {
                                            "type": "link",
                                            "url": "https://github.com/ohcnetwork/care_fe/pull/12524",
                                            "text": "fix: Misalignment and inconsistency in the UI of 'Add Files' dropdown in encounter files"
                                        }
                                    ]
                                },
                                {
                                    "type": "rich_text_section",
                                    "elements": [
                                        {
                                            "type": "text",
                                            "text": "Opened and started working on "
                                        },
                                        {
                                            "type": "link",
                                            "url": "https://github.com/ohcnetwork/care_fe/issues/12526",
                                            "text": "Enhance the UI of the patient encounters file menu for mobile screens"
                                        },
                                        {
                                            "type": "text",
                                            "text": ", Later it became clear that an issue addressing the same prob already exists"
                                        }
                                    ]
                                }
                            ],
                            "style": "bullet",
                            "indent": 0,
                            "border": 0
                        },
                        {
                            "type": "rich_text_section",
                            "elements": [
                                {
                                    "type": "text",
                                    "text": "Next\n"
                                }
                            ]
                        },
                        {
                            "type": "rich_text_list",
                            "elements": [
                                {
                                    "type": "rich_text_section",
                                    "elements": [
                                        {
                                            "type": "text",
                                            "text": "Take it easy"
                                        }
                                    ]
                                },
                                {
                                    "type": "rich_text_section",
                                    "elements": [
                                        {
                                            "type": "text",
                                            "text": "Find more bugs"
                                        }
                                    ]
                                }
                            ],
                            "style": "bullet",
                            "indent": 0,
                            "border": 0
                        }
                    ]
                }
            ]
        }
    ],
    "2025-06-10 00:00:00": [
        {
            "user": "U07ERHUJ3A9",
            "type": "message",
            "ts": "1749577013.497059",
            "client_msg_id": "5a483ab1-0e8f-43ab-a5a7-a49f9c5824b8",
            "text": "7th June\n\u2022 Didn't get much done\n8th, 9th and 10th June\n\u2022 Opened <https://github.com/ohcnetwork/care_fe/issues/12526|#12526>, got closed cause issue already exists.\n\u2022 Opened <https://github.com/ohcnetwork/care_fe/issues/12545|#12545>, got closed cause it was the browser's issue.\n\u2022 Got assigned to <https://github.com/ohcnetwork/care_fe/issues/12565|#12565>\n\u2022 Raised <https://github.com/ohcnetwork/care_fe/pull/12573|#12573>\n\u2022 Opened <https://github.com/ohcnetwork/care_fe/issues/12582|#12582>\nNext:\n\u2022 Raise PR for <https://github.com/ohcnetwork/care_fe/issues/12582|#12582>\n\u2022 Find more bugs",
            "team": "TC99SV7B6",
            "blocks": [
                {
                    "type": "rich_text",
                    "block_id": "SjfQT",
                    "elements": [
                        {
                            "type": "rich_text_section",
                            "elements": [
                                {
                                    "type": "text",
                                    "text": "7th June\n"
                                }
                            ]
                        },
                        {
                            "type": "rich_text_list",
                            "elements": [
                                {
                                    "type": "rich_text_section",
                                    "elements": [
                                        {
                                            "type": "text",
                                            "text": "Didn't get much done"
                                        }
                                    ]
                                }
                            ],
                            "style": "bullet",
                            "indent": 0,
                            "border": 0
                        },
                        {
                            "type": "rich_text_section",
                            "elements": [
                                {
                                    "type": "text",
                                    "text": "8th, 9th and 10th June\n"
                                }
                            ]
                        },
                        {
                            "type": "rich_text_list",
                            "elements": [
                                {
                                    "type": "rich_text_section",
                                    "elements": [
                                        {
                                            "type": "text",
                                            "text": "Opened "
                                        },
                                        {
                                            "type": "link",
                                            "url": "https://github.com/ohcnetwork/care_fe/issues/12526",
                                            "text": "#12526",
                                            "unsafe": true
                                        },
                                        {
                                            "type": "text",
                                            "text": ", got closed cause issue already exists."
                                        }
                                    ]
                                },
                                {
                                    "type": "rich_text_section",
                                    "elements": [
                                        {
                                            "type": "text",
                                            "text": "Opened "
                                        },
                                        {
                                            "type": "link",
                                            "url": "https://github.com/ohcnetwork/care_fe/issues/12545",
                                            "text": "#12545",
                                            "unsafe": true
                                        },
                                        {
                                            "type": "text",
                                            "text": ", got closed cause it was the browser's issue."
                                        }
                                    ]
                                },
                                {
                                    "type": "rich_text_section",
                                    "elements": [
                                        {
                                            "type": "text",
                                            "text": "Got assigned to "
                                        },
                                        {
                                            "type": "link",
                                            "url": "https://github.com/ohcnetwork/care_fe/issues/12565",
                                            "text": "#12565",
                                            "unsafe": true
                                        }
                                    ]
                                },
                                {
                                    "type": "rich_text_section",
                                    "elements": [
                                        {
                                            "type": "text",
                                            "text": "Raised "
                                        },
                                        {
                                            "type": "link",
                                            "url": "https://github.com/ohcnetwork/care_fe/pull/12573",
                                            "text": "#12573",
                                            "unsafe": true
                                        }
                                    ]
                                },
                                {
                                    "type": "rich_text_section",
                                    "elements": [
                                        {
                                            "type": "text",
                                            "text": "Opened "
                                        },
                                        {
                                            "type": "link",
                                            "url": "https://github.com/ohcnetwork/care_fe/issues/12582",
                                            "text": "#12582",
                                            "unsafe": true
                                        }
                                    ]
                                }
                            ],
                            "style": "bullet",
                            "indent": 0,
                            "border": 0
                        },
                        {
                            "type": "rich_text_section",
                            "elements": [
                                {
                                    "type": "text",
                                    "text": "Next:\n"
                                }
                            ]
                        },
                        {
                            "type": "rich_text_list",
                            "elements": [
                                {
                                    "type": "rich_text_section",
                                    "elements": [
                                        {
                                            "type": "text",
                                            "text": "Raise PR for "
                                        },
                                        {
                                            "type": "link",
                                            "url": "https://github.com/ohcnetwork/care_fe/issues/12582",
                                            "text": "#12582",
                                            "unsafe": true
                                        }
                                    ]
                                },
                                {
                                    "type": "rich_text_section",
                                    "elements": [
                                        {
                                            "type": "text",
                                            "text": "Find more bugs"
                                        }
                                    ]
                                }
                            ],
                            "style": "bullet",
                            "indent": 0,
                            "border": 0
                        }
                    ]
                }
            ]
        }
    ]
}