{
  "last_updated": "2025-07-04T14:47:27.000Z",
  "activity": [
    {
      "type": "pr_merged",
      "title": "ohcnetwork/leaderboard-data#122",
      "time": "2025-07-04T14:47:27.000Z",
      "link": "https://github.com/ohcnetwork/leaderboard-data/pull/122",
      "text": "Contributor file updated",
      "turnaround_time": 96753
    },
    {
      "type": "comment_created",
      "title": "ohcnetwork/leaderboard-data#122",
      "time": "2025-07-03T11:58:25.000Z",
      "link": "https://github.com/ohcnetwork/leaderboard-data/pull/122#issuecomment-3032000795",
      "text": "hey @AdityaJ2305 , i have updated the role.\r\n"
    },
    {
      "type": "pr_opened",
      "title": "ohcnetwork/leaderboard-data#122",
      "time": "2025-07-03T11:54:55.000Z",
      "link": "https://github.com/ohcnetwork/leaderboard-data/pull/122",
      "text": "Contributor file updated"
    },
    {
      "type": "comment_created",
      "title": "ohcnetwork/care_fe#10483",
      "time": "2025-02-09T09:52:41.000Z",
      "link": "https://github.com/ohcnetwork/care_fe/issues/10483#issuecomment-2646153260",
      "text": "Hi @shivankacker  I noticed that this issue is currently self-assigned to you. I am interested in working on this issue and it seems like a good first issue to me. Would it be possible for you to reassign it to me?"
    }
  ],
  "open_prs": [],
  "authored_issue_and_pr": []
}